myfinances/__init__.py
myfinances/base_service.py
myfinances/client.py
myfinances/models.py
myfinances/clients/__init__.py
myfinances/clients/models.py
myfinances/clients/service.py
myfinances/finance/__init__.py
myfinances/finance/invoices/__init__.py
myfinances/finance/invoices/models.py
myfinances/finance/invoices/service.py
MyFinances-0.1.1.dist-info/LICENSE
MyFinances-0.1.1.dist-info/METADATA
MyFinances-0.1.1.dist-info/WHEEL
MyFinances-0.1.1.dist-info/top_level.txt
MyFinances-0.1.1.dist-info/RECORD
