Metadata-Version: 2.1
Name: MyFinances
Version: 0.1.1
Summary: A python client package to interact with the MyFinances API through python.
Author-email: Trey <trey@strelix.org>
License: MIT License
Project-URL: Homepage, https://github.com/Strelix/MyFinances-python
Project-URL: Issues, https://github.com/Strelix/MyFinances-python/issues
Classifier: Environment :: Web Environment
Classifier: Intended Audience :: Developers
Classifier: License :: OSI Approved :: MIT License
Classifier: Operating System :: OS Independent
Classifier: Programming Language :: Python
Classifier: Programming Language :: Python :: 3
Classifier: Programming Language :: Python :: 3 :: Only
Classifier: Programming Language :: Python :: 3.10
Classifier: Programming Language :: Python :: 3.11
Classifier: Programming Language :: Python :: 3.12
Requires-Python: >=3.10
License-File: LICENSE
